{
  "keep": {
    "days": true,
    "amount": 31
  },
  "auditLog": "E:\\newELv\\erlvzihuwai\\donkeys-server\\logs\\cool-admin\\.7bb94179aecb59e6de1e4e269ca36f5c1cc3f575-audit.json",
  "files": [
    {
      "date": 1711030958746,
      "name": "E:\\newELv\\erlvzihuwai\\donkeys-server\\logs\\cool-admin\\midway-agent.log.2024-03-21",
      "hash": "e656d603fef078134946ecf415aa3e09"
    },
    {
      "date": 1711037140254,
      "name": "E:\\newELv\\erlvzihuwai\\donkeys-server\\logs\\cool-admin\\midway-agent.log.2024-03-22",
      "hash": "132c743f6a790a8d5c0a9f6fbba1fd05"
    }
  ],
  "hashType": "md5"
}